management/__init__.py
management/commands/__init__.py
management/commands/create_escalation_exclusions.py
management/commands/create_queue_permissions.py
management/commands/create_usersettings.py
management/commands/escalate_tickets.py
management/commands/get_email.py
migrations/0001_initial.py
migrations/0002_populate_usersettings.py
migrations/0003_initial_data_import.py
migrations/0004_add_per_queue_staff_membership.py
migrations/0005_queues_no_null.py
migrations/0006_email_maxlength.py
migrations/0007_max_length_by_integer.py
migrations/0008_extra_for_permissions.py
migrations/0009_migrate_queuemembership.py
migrations/0010_remove_queuemembership.py
migrations/0011_admin_related_improvements.py
migrations/0012_queue_default_owner.py
migrations/0013_email_box_local_dir_and_logging.py
migrations/0014_usersettings_related_name.py
migrations/0015_expand_permission_name_size.py
migrations/0016_alter_model_options.py
migrations/0017_default_owner_on_delete_null.py
migrations/0018_fix_migrations.py
migrations/__init__.py
templatetags/__init__.py
templatetags/in_list.py
templatetags/load_helpdesk_settings.py
templatetags/saved_queries.py
templatetags/ticket_to_link.py
templatetags/user_admin_url.py
tests/__init__.py
tests/helpers.py
tests/test_attachments.py
tests/test_get_email.py
tests/test_login.py
tests/test_navigation.py
tests/test_per_queue_staff_permission.py
tests/test_public_actions.py
tests/test_savequery.py
tests/test_ticket_actions.py
tests/test_ticket_lookup.py
tests/test_ticket_submission.py
tests/test_usersettings.py
tests/urls.py
views/__init__.py
views/feeds.py
views/kb.py
views/login.py
views/public.py
views/staff.py
ticketing_achange-1.0.dist-info/METADATA
ticketing_achange-1.0.dist-info/WHEEL
ticketing_achange-1.0.dist-info/top_level.txt
ticketing_achange-1.0.dist-info/RECORD
