Metadata-Version: 2.1
Name: ticketing-achange
Version: 1.0
Summary: ticketing app 
Home-page: UNKNOWN
Author: alireza-76
Author-email: alirezaghaempanah2015@gmail.com
License: achange
Platform: UNKNOWN
